clyp/ErrorHandling.py
clyp/__init__.py
clyp/__main__.py
clyp/cli.py
clyp/formatter.py
clyp/importer.py
clyp/precheck.py
clyp/stdlib.py
clyp/transpiler.py
clyp-2.1.0.dist-info/licenses/LICENSE
clyp-2.1.0.dist-info/METADATA
clyp-2.1.0.dist-info/WHEEL
clyp-2.1.0.dist-info/entry_points.txt
clyp-2.1.0.dist-info/top_level.txt
clyp-2.1.0.dist-info/RECORD
