Metadata-Version: 2.4
Name: clyp
Version: 2.1.0
Summary: Clyp is a programming language that transpiles to Python.
Home-page: https://clyp.codesft.dev/
Author: CodeSoft
License: MIT
Project-URL: Source, https://github.com/clyplang/clyp
License-File: LICENSE
Requires-Dist: typeguard
Requires-Dist: click
Requires-Dist: requests
Requires-Dist: ycpm
Requires-Dist: cython
Requires-Dist: black
Requires-Dist: orjson
Dynamic: author
Dynamic: description
Dynamic: description-content-type
Dynamic: home-page
Dynamic: license
Dynamic: license-file
Dynamic: project-url
Dynamic: requires-dist
Dynamic: summary
